Metadata-Version: 2.1
Name: python-vera
Version: 1.1
Summary: Python library to allow control of a Vera home automation hub
Home-page: https://github.com/cybermaggedon/pyvera
Author: Cybermaggedon
Author-email: mark@cyberapocalypse.co.uk
License: UNKNOWN
Download-URL: https://github.com/cybermaggedon/pyvera/archive/refs/tags/v1.1.tar.gz
Platform: UNKNOWN
Classifier: Programming Language :: Python :: 3
Classifier: License :: OSI Approved :: GNU General Public License v3 or later (GPLv3+)
Classifier: Operating System :: OS Independent
Requires-Python: >=3.0
